blastbot_cloud_api/__init__.py
blastbot_cloud_api/api.py
blastbot_cloud_api/auth.py
blastbot_cloud_api/models/__init__.py
blastbot_cloud_api/models/control.py
blastbot_cloud_api/models/device.py
blastbot_cloud_api_python-0.1.2.dist-info/LICENSE
blastbot_cloud_api_python-0.1.2.dist-info/METADATA
blastbot_cloud_api_python-0.1.2.dist-info/WHEEL
blastbot_cloud_api_python-0.1.2.dist-info/top_level.txt
blastbot_cloud_api_python-0.1.2.dist-info/RECORD
