Metadata-Version: 2.1
Name: blastbot-cloud-api-python
Version: 0.1.2
Summary: Library for interfacing with Blastbot Cloud
Home-page: https://github.com/Rodmg/blastbot-cloud-api-python
Author: Rodrigo Mendez
Author-email: rmendez@makerlab.mx
License: Apache License Version 2.0
Platform: UNKNOWN
Requires-Dist: aiohttp
